LICENSE.txt
MANIFEST.in
README.md
pyproject.toml
setup.cfg
src/proj_man_zdo/__init__.py
src/proj_man_zdo/common.py
src/proj_man_zdo/constants_version.py
src/proj_man_zdo/git.py
src/proj_man_zdo/navigate.py
src/proj_man_zdo/os_specific.py
src/proj_man_zdo/requirements.py
src/proj_man_zdo/run_cmds.py
src/proj_man_zdo/various.py
src/proj_man_zdo/zdo_base.py
src/proj_man_zdo.egg-info/PKG-INFO
src/proj_man_zdo.egg-info/SOURCES.txt
src/proj_man_zdo.egg-info/dependency_links.txt
src/proj_man_zdo.egg-info/requires.txt
src/proj_man_zdo.egg-info/top_level.txt