Metadata-Version: 2.4
Name: proj-man-zdo
Version: 0.1.1
Summary: project management zdo
Author-email: "J. Arrizza" <cppgent0@gmail.com>
Maintainer-email: "J. Arrizza" <cppgent0@gmail.com>
License-Expression: MIT
Project-URL: Website, https://arrizza.com/python-proj-man-zdo
Project-URL: Source, https://bitbucket.org/arrizza-public/proj-man-zdo/src/master
Project-URL: Download, https://bitbucket.org/arrizza-public/proj-man-zdo/get/master.zip
Keywords: project,management
Classifier: Development Status :: 3 - Alpha
Classifier: Environment :: Console
Classifier: Topic :: Utilities
Classifier: Intended Audience :: Developers
Classifier: Programming Language :: Python :: 3.10
Classifier: Programming Language :: Python :: 3.12
Requires-Python: >=3.9
License-File: LICENSE.txt
Requires-Dist: falcon-logger
Dynamic: license-file
